{
  "source": "reddit",
  "label": "Reddit — r/all, past hour",
  "fetched_at": "2026-05-02T11:06:30.940Z",
  "items": [
    {
      "rank": 1,
      "title": "It's official: No woman in England or Wales can be prosecuted for an abortion any more",
      "url": "https://reddit.com/r/UpliftingNews/comments/1t1m1c7/its_official_no_woman_in_england_or_wales_can_be/",
      "external_url": "https://www.cosmopolitan.com/uk/reports/a71163004/england-wales-decriminalise-abortion/",
      "subreddit": "r/UpliftingNews",
      "score": 1471,
      "comments": 51,
      "author": "Alarming-Safety3200"
    },
    {
      "rank": 2,
      "title": "It's official: No woman in England or Wales can be prosecuted for an abortion any more",
      "url": "https://reddit.com/r/europe/comments/1t1lv0o/its_official_no_woman_in_england_or_wales_can_be/",
      "external_url": "https://www.cosmopolitan.com/uk/reports/a71163004/england-wales-decriminalise-abortion/",
      "subreddit": "r/europe",
      "score": 1206,
      "comments": 70,
      "author": "Alarming-Safety3200"
    },
    {
      "rank": 3,
      "title": "Look at the man driving the tram",
      "url": "https://reddit.com/r/funny/comments/1t1me5j/look_at_the_man_driving_the_tram/",
      "external_url": "https://i.redd.it/1fb43mabdpyg1.jpeg",
      "subreddit": "r/funny",
      "score": 834,
      "comments": 12,
      "author": "tahirahaha"
    },
    {
      "rank": 4,
      "title": "It's happening again...",
      "url": "https://reddit.com/r/formuladank/comments/1t1m3lx/its_happening_again/",
      "external_url": "https://i.redd.it/ks7lev79apyg1.png",
      "subreddit": "r/formuladank",
      "score": 683,
      "comments": 41,
      "author": "joaopaulofoo"
    },
    {
      "rank": 5,
      "title": "MP: Most valami olyasmibe kezdünk, ami ritkán adatik meg egy országnak.",
      "url": "https://reddit.com/r/hungary/comments/1t1luwm/mp_most_valami_olyasmibe_kezdünk_ami_ritkán/",
      "external_url": "https://i.redd.it/altwrhcv7pyg1.jpeg",
      "subreddit": "r/hungary",
      "score": 563,
      "comments": 34,
      "author": "vivuss77"
    },
    {
      "rank": 6,
      "title": "It's official: No woman in England or Wales can be prosecuted for an abortion any more",
      "url": "https://reddit.com/r/worldnews/comments/1t1luv9/its_official_no_woman_in_england_or_wales_can_be/",
      "external_url": "https://www.cosmopolitan.com/uk/reports/a71163004/england-wales-decriminalise-abortion/",
      "subreddit": "r/worldnews",
      "score": 523,
      "comments": 23,
      "author": "Alarming-Safety3200"
    },
    {
      "rank": 7,
      "title": "Did bro just ungay himself",
      "url": "https://reddit.com/r/shitposting/comments/1t1luog/did_bro_just_ungay_himself/",
      "external_url": "https://i.redd.it/vq8qs9ws7pyg1.jpeg",
      "subreddit": "r/shitposting",
      "score": 492,
      "comments": 41,
      "author": "Low-Major-5486"
    },
    {
      "rank": 8,
      "title": "Do studios even care anymore",
      "url": "https://reddit.com/r/memes/comments/1t1m3mf/do_studios_even_care_anymore/",
      "external_url": "https://i.redd.it/cqrmzbgbapyg1.jpeg",
      "subreddit": "r/memes",
      "score": 494,
      "comments": 41,
      "author": "Entire-Researcher519"
    },
    {
      "rank": 9,
      "title": "Ich will meiner Freundin nicht beim kacken zusehen!",
      "url": "https://reddit.com/r/luftablassen/comments/1t1m0cp/ich_will_meiner_freundin_nicht_beim_kacken_zusehen/",
      "external_url": null,
      "subreddit": "r/luftablassen",
      "score": 331,
      "comments": 77,
      "author": "beezz187"
    },
    {
      "rank": 10,
      "title": "Furry_irl",
      "url": "https://reddit.com/r/furry_irl/comments/1t1lzt3/furry_irl/",
      "external_url": "https://i.redd.it/l4f9h4489pyg1.jpeg",
      "subreddit": "r/furry_irl",
      "score": 286,
      "comments": 11,
      "author": "DL2828"
    },
    {
      "rank": 11,
      "title": "Idiot forgot chambered round in mere seconds",
      "url": "https://reddit.com/r/Idiotswithguns/comments/1t1lv2j/idiot_forgot_chambered_round_in_mere_seconds/",
      "external_url": "https://v.redd.it/trjmqxqw7pyg1",
      "subreddit": "r/Idiotswithguns",
      "score": 222,
      "comments": 36,
      "author": "BinLadenSwallowCock"
    },
    {
      "rank": 12,
      "title": "Baby spe and the world’s fastest cutting board",
      "url": "https://reddit.com/r/UmaMusume/comments/1t1lzg4/baby_spe_and_the_worlds_fastest_cutting_board/",
      "external_url": "https://i.redd.it/umwymcx49pyg1.jpeg",
      "subreddit": "r/UmaMusume",
      "score": 212,
      "comments": 11,
      "author": "Acrobatic-Track-5764"
    },
    {
      "rank": 13,
      "title": "Can't beat granny",
      "url": "https://reddit.com/r/MadeMeSmile/comments/1t1lzi7/cant_beat_granny/",
      "external_url": "https://v.redd.it/9ddk20l59pyg1",
      "subreddit": "r/MadeMeSmile",
      "score": 216,
      "comments": 17,
      "author": "PorkyPain"
    },
    {
      "rank": 14,
      "title": "3.4 | About Character Voiceover Language Switch via Seele",
      "url": "https://reddit.com/r/WutheringWavesLeaks/comments/1t1m9rj/34_about_character_voiceover_language_switch_via/",
      "external_url": "https://i.redd.it/jgirq5lxbpyg1.png",
      "subreddit": "r/WutheringWavesLeaks",
      "score": 200,
      "comments": 49,
      "author": "ThatWill4724"
    },
    {
      "rank": 15,
      "title": "What's happening around ???",
      "url": "https://reddit.com/r/pune/comments/1t1m8wd/whats_happening_around/",
      "external_url": "https://v.redd.it/ew0tkcptbpyg1",
      "subreddit": "r/pune",
      "score": 202,
      "comments": 33,
      "author": "soyaaabeann"
    },
    {
      "rank": 16,
      "title": "Deine Se*ualität interessiert mich einen Scheiß",
      "url": "https://reddit.com/r/luftablassen/comments/1t1m72x/deine_seualität_interessiert_mich_einen_scheiß/",
      "external_url": null,
      "subreddit": "r/luftablassen",
      "score": 196,
      "comments": 150,
      "author": "TheBabySnail"
    },
    {
      "rank": 17,
      "title": "Such a specific amount of time that she's going to wear clothing he picks out for her",
      "url": "https://reddit.com/r/oddlyspecific/comments/1t1ltv0/such_a_specific_amount_of_time_that_shes_going_to/",
      "external_url": "https://i.redd.it/dkt17g9l7pyg1.png",
      "subreddit": "r/oddlyspecific",
      "score": 195,
      "comments": 4,
      "author": "BeingBetter42"
    },
    {
      "rank": 18,
      "title": "Extremely underrated bullet type",
      "url": "https://reddit.com/r/Terraria/comments/1t1ltu6/extremely_underrated_bullet_type/",
      "external_url": "https://i.redd.it/dde2qzwk7pyg1.jpeg",
      "subreddit": "r/Terraria",
      "score": 186,
      "comments": 21,
      "author": "OverTea5"
    },
    {
      "rank": 19,
      "title": "ich_iel",
      "url": "https://reddit.com/r/ich_iel/comments/1t1lvke/ich_iel/",
      "external_url": "https://i.redd.it/lslcst628pyg1.jpeg",
      "subreddit": "r/ich_iel",
      "score": 173,
      "comments": 6,
      "author": "avoy_e"
    },
    {
      "rank": 20,
      "title": "Mini roses made by hand",
      "url": "https://reddit.com/r/oddlysatisfying/comments/1t1lv2v/mini_roses_made_by_hand/",
      "external_url": "https://v.redd.it/3mx5d3jw7pyg1",
      "subreddit": "r/oddlysatisfying",
      "score": 171,
      "comments": 13,
      "author": "Genesis_the_god_"
    },
    {
      "rank": 21,
      "title": "Ridon: Sara Duterte expected to be impeached within 2 weeks",
      "url": "https://reddit.com/r/Philippines/comments/1t1m34l/ridon_sara_duterte_expected_to_be_impeached/",
      "external_url": "https://i.redd.it/3z8yltg6apyg1.jpeg",
      "subreddit": "r/Philippines",
      "score": 168,
      "comments": 30,
      "author": "Rare_Independent0310"
    },
    {
      "rank": 22,
      "title": "Trump lives in the glassiest of glass houses.",
      "url": "https://reddit.com/r/MurderedByWords/comments/1t1mmny/trump_lives_in_the_glassiest_of_glass_houses/",
      "external_url": "https://i.redd.it/n625sasofpyg1.jpeg",
      "subreddit": "r/MurderedByWords",
      "score": 174,
      "comments": 6,
      "author": "c-k-q99903"
    },
    {
      "rank": 23,
      "title": "Prince Jackson, son of Michael Jackson, shows his father’s home recording studio 🤯",
      "url": "https://reddit.com/r/whoathatsinteresting/comments/1t1m2t1/prince_jackson_son_of_michael_jackson_shows_his/",
      "external_url": "https://v.redd.it/zu6walqy9pyg1",
      "subreddit": "r/whoathatsinteresting",
      "score": 159,
      "comments": 44,
      "author": "eternviking"
    },
    {
      "rank": 24,
      "title": "Jedes Mal beim Autofahren",
      "url": "https://reddit.com/r/JulesYT/comments/1t1m1hv/jedes_mal_beim_autofahren/",
      "external_url": "https://i.redd.it/rf00c78p9pyg1.png",
      "subreddit": "r/JulesYT",
      "score": 157,
      "comments": 11,
      "author": "riasat93"
    },
    {
      "rank": 25,
      "title": "47906",
      "url": "https://reddit.com/r/countwithchickenlady/comments/1t1lx49/47906/",
      "external_url": "https://i.redd.it/2uylw28g8pyg1.jpeg",
      "subreddit": "r/countwithchickenlady",
      "score": 154,
      "comments": 6,
      "author": "Phoeeebe42"
    }
  ]
}